powerline_wttr/__init__.py
powerline_wttr/weather.py
powerline_wttr-0.1.dist-info/METADATA
powerline_wttr-0.1.dist-info/WHEEL
powerline_wttr-0.1.dist-info/RECORD
