Metadata-Version: 2.3
Name: powerline-wttr
Version: 0.1
Summary: A Powerline segment for fetching and showing the weather in the current location
Author-email: Penpen7 <Raosys@live.jp>
License: MIT License
Keywords: powerline,segment,weather
Classifier: Environment :: Console
Classifier: Intended Audience :: Developers
Classifier: License :: OSI Approved :: MIT License
Classifier: Topic :: Terminals
Requires-Python: >=3.12
Requires-Dist: powerline-status
Requires-Dist: requests
